pyl3dmd/__init__.py
pyl3dmd/cpsa.py
pyl3dmd/descriptors1set.py
pyl3dmd/descriptors2set.py
pyl3dmd/descriptors3set.py
pyl3dmd/descriptors4set.py
pyl3dmd/descriptors5set.py
pyl3dmd/descriptors6set.py
pyl3dmd/distancedistancematrixdescriptors.py
pyl3dmd/geary.py
pyl3dmd/geometricdescriptors.py
pyl3dmd/getadjacencyanddistancematrices.py
pyl3dmd/getatomicproperties.py
pyl3dmd/getaway.py
pyl3dmd/getinfofromlammpsdatafile.py
pyl3dmd/getinfofromlammpstrajfile.py
pyl3dmd/moran.py
pyl3dmd/moreaubroto.py
pyl3dmd/morse.py
pyl3dmd/pyl3dmd.py
pyl3dmd/rdf.py
pyl3dmd/removehydrogenfrommolecule.py
pyl3dmd/topologyconnectivity3Ddescriptors.py
pyl3dmd/whim.py
pyl3dmd-0.1.1.dist-info/METADATA
pyl3dmd-0.1.1.dist-info/WHEEL
pyl3dmd-0.1.1.dist-info/top_level.txt
pyl3dmd-0.1.1.dist-info/RECORD
