Metadata-Version: 2.1
Name: pyl3dmd
Version: 0.1.1
Summary: Python LAMMPS 3-Dimensional Molecular Dynamics/Descriptors
Author: Pawan Panwar, Quanpeng Yang, Ashlie Martini
Author-email: panwarp@msoe.edu
Keywords: Python,LAMMPS,Molecular Dynamics Simulations,Molecular Descriptors,Machine Learning,MD Simulations,3-Dimensional
Classifier: Development Status :: 3 - Alpha
Classifier: Intended Audience :: Education
Classifier: Programming Language :: Python :: 2
Classifier: Programming Language :: Python :: 3
Classifier: Operating System :: MacOS :: MacOS X
Classifier: Operating System :: Microsoft :: Windows
